README.txt
setup.cfg
setup.py
src/mekk/__init__.py
src/mekk.feeds.egg-info/PKG-INFO
src/mekk.feeds.egg-info/SOURCES.txt
src/mekk.feeds.egg-info/dependency_links.txt
src/mekk.feeds.egg-info/entry_points.txt
src/mekk.feeds.egg-info/namespace_packages.txt
src/mekk.feeds.egg-info/requires.txt
src/mekk.feeds.egg-info/top_level.txt
src/mekk.feeds.egg-info/zip-safe
src/mekk/feeds/__init__.py
src/mekk/feeds/version.py
src/mekk/feeds/greader2org/__init__.py
src/mekk/feeds/greader2org/base_command.py
src/mekk/feeds/greader2org/helpers.py
src/mekk/feeds/greader2org/initial_load.py
src/mekk/feeds/greader2org/run.py
src/mekk/feeds/greader2org/settings.py
src/mekk/feeds/greader2org/update_from_google.py
src/mekk/feeds/greader2org/update_to_google.py
src/mekk/feeds/orgfile/__init__.py
src/mekk/feeds/orgfile/org_file.py
src/mekk/feeds/orgfile/org_parse.py