Metadata-Version: 1.0
Name: mekk.feeds
Version: 1.4.3
Summary: RSS scripting
Home-page: http://mekk.waw.pl/
Author: Marcin Kasperski
Author-email: Marcin.Kasperski@mekk.waw.pl
License: BSD
Keywords: org
Platform: UNKNOWN
Classifier: Programming Language :: Python
Classifier: Intended Audience :: Developers
Classifier: Topic :: Software Development :: Libraries :: Python Modules
